tornado_middleware/__init__.py
tornado_middleware/commons.py
tornado_middleware-1.2.3.dist-info/LICENSE
tornado_middleware-1.2.3.dist-info/METADATA
tornado_middleware-1.2.3.dist-info/WHEEL
tornado_middleware-1.2.3.dist-info/top_level.txt
tornado_middleware-1.2.3.dist-info/RECORD
